zoltraakklein/__init__.py
zoltraakklein/_yaml_manager.py
zoltraakklein/_yaml_manager_pending_upgrade.py
zoltraakklein/config.py
zoltraakklein/utils.py
zoltraakklein/yaml_manager.py
zoltraakklein/zoltraakklein.py
zoltraakklein/architect/3d_meshy.py
zoltraakklein/architect/architect_common.py
zoltraakklein/architect/epub.py
zoltraakklein/architect/epub_picture.py
zoltraakklein/architect/image_dalle.py
zoltraakklein/architect/image_stable_diffusion.py
zoltraakklein/architect/marp_presentation.py
zoltraakklein/architect/marp_script.py
zoltraakklein/architect/mermaid_chart.py
zoltraakklein/architect/video_from_presentation.py
zoltraakklein/architect/video_pikapikapika.py
zoltraakklein/architect/virtual_character.py
zoltraakklein/architect/voice_elevenlabs.py
zoltraakklein/architect/voice_voicevox.py
zoltraakklein/architect/writer.py
zoltraakklein/compilers/akira_papa.md
zoltraakklein/compilers/book_business.md
zoltraakklein/compilers/book_picture.md
zoltraakklein/compilers/book_technical.md
zoltraakklein/compilers/business_negotiation.md
zoltraakklein/compilers/business_plan.md
zoltraakklein/compilers/cooking_recipe.md
zoltraakklein/compilers/general_proposal.md
zoltraakklein/compilers/marketing_research.md
zoltraakklein/compilers/outfit_idea.md
zoltraakklein/compilers/presentation_marp.md
zoltraakklein/compilers/project_rd.md
zoltraakklein/compilers/software_development.md
zoltraakklein/compilers/strategic_consultant.md
zoltraakklein/compilers/travel_plan.md
zoltraakklein/compilers/virtual_human.md
zoltraakklein/compilers/web_article.md
zoltraakklein/instructions/akira_papa.yaml
zoltraakklein/instructions/book_business.yaml
zoltraakklein/instructions/book_picture.yaml
zoltraakklein/instructions/book_technical.yaml
zoltraakklein/instructions/business_negotiation.yaml
zoltraakklein/instructions/business_plan.yaml
zoltraakklein/instructions/cooking_recipe.yaml
zoltraakklein/instructions/general_proposal.yaml
zoltraakklein/instructions/marketing_research.yaml
zoltraakklein-1.0.7.dist-info/LICENSE
zoltraakklein-1.0.7.dist-info/METADATA
zoltraakklein-1.0.7.dist-info/WHEEL
zoltraakklein-1.0.7.dist-info/top_level.txt
zoltraakklein-1.0.7.dist-info/RECORD
