Metadata-Version: 2.1
Name: zoltraakklein
Version: 1.0.7
Summary: Simplified class for Zoltraak, a digital content production framework by working with LLMs and generative AIs.
Home-page: https://pypi.org/project/zoltraakklein/
Author: Daisuke Yamaguchi
Author-email: daicom0204@gmail.com
Project-URL: Homepage, https://habatakurikei.com/
Project-URL: GitHub, https://github.com/Habatakurikei/zoltraakklein
Classifier: Development Status :: 3 - Alpha
Classifier: Intended Audience :: Developers
Classifier: License :: OSI Approved :: MIT License
Classifier: Operating System :: OS Independent
Classifier: Programming Language :: Python :: 3
Classifier: Programming Language :: Python :: 3.10
Classifier: Programming Language :: Python :: 3.11
Classifier: Programming Language :: Python :: 3.12
Requires-Python: >=3.10
License-File: LICENSE
Requires-Dist: llmmaster==0.5.0
Requires-Dist: opencv-python>=4.10.0.84
Requires-Dist: moviepy>=1.0.3
Provides-Extra: dev
Requires-Dist: pytest>=6.0; extra == "dev"
Requires-Dist: flake8>=6.0; extra == "dev"
